ai/__init__.py
ai/codes/Chapter.10.ipynb
ai/codes/Chapter.2.ipynb
ai/codes/Chapter.3.ipynb
ai/codes/Chapter.4 数据预处理.ipynb
ai/codes/Chapter.5.ipynb
ai/codes/Chapter.6.ipynb
ai/codes/Chapter.7.ipynb
ai/codes/Chapter.8.ipynb
ai/codes/Chapter.9.ipynb
ai/codes/__init__.py
ai/codes/example.jpg
ai/codes/iris_decision_tree
ai/codes/jn.cmd
ai/codes/model.joblib
ai/codes/model.pkl
ai/codes/.ipynb_checkpoints/Chapter.10-checkpoint.ipynb
ai/codes/.ipynb_checkpoints/Chapter.2-checkpoint.ipynb
ai/codes/.ipynb_checkpoints/Chapter.3-checkpoint.ipynb
ai/codes/.ipynb_checkpoints/Chapter.4 数据预处理-checkpoint.ipynb
ai/codes/.ipynb_checkpoints/Chapter.5-checkpoint.ipynb
ai/codes/.ipynb_checkpoints/Chapter.6-checkpoint.ipynb
ai/codes/.ipynb_checkpoints/Chapter.7-checkpoint.ipynb
ai/codes/.ipynb_checkpoints/Chapter.8-checkpoint.ipynb
ai/codes/.ipynb_checkpoints/Chapter.9-checkpoint.ipynb
ai/codes/.ipynb_checkpoints/Untitled-checkpoint.ipynb
ai/codes/.ipynb_checkpoints/Untitled1-checkpoint.ipynb
ai/codes/.ipynb_checkpoints/Untitled2-checkpoint.ipynb
ai/codes/.ipynb_checkpoints/Untitled3-checkpoint.ipynb
ai/codes/.ipynb_checkpoints/Untitled4-checkpoint.ipynb
ai/codes/.ipynb_checkpoints/Untitled5-checkpoint.ipynb
ai/codes/.ipynb_checkpoints/iris_decision_tree-checkpoint
ai/codes/data/openml/openml.org/api/v1/json/data/61.gz
ai/codes/data/openml/openml.org/api/v1/json/data/features/61.gz
ai/codes/data/openml/openml.org/api/v1/json/data/list/data_name/iris/limit/2/data_version/1.gz
ai/codes/data/openml/openml.org/api/v1/json/data/qualities/61.gz
ai/codes/data/openml/openml.org/data/v1/download/61.gz
ai/datasets/__init__.py
ai/ml/__init__.py
ML_Education_Tools-24.1.18.dist-info/METADATA
ML_Education_Tools-24.1.18.dist-info/WHEEL
ML_Education_Tools-24.1.18.dist-info/entry_points.txt
ML_Education_Tools-24.1.18.dist-info/top_level.txt
ML_Education_Tools-24.1.18.dist-info/RECORD
